Helsing/__init__.py
Helsing/colour_swap.py
Helsing/count_form.py
Helsing/main.py
Helsing/models.py
Helsing-0.0.2.post1.dist-info/LICENSE
Helsing-0.0.2.post1.dist-info/METADATA
Helsing-0.0.2.post1.dist-info/WHEEL
Helsing-0.0.2.post1.dist-info/top_level.txt
Helsing-0.0.2.post1.dist-info/RECORD
