Metadata-Version: 2.1
Name: Helsing
Version: 0.0.2.post1
Summary: Compares specific data for misc business purposes.
Home-page: UNKNOWN
Author: Demosius
Author-email: a.m.penny@hotmail.com
License: UNKNOWN
Platform: UNKNOWN
Classifier: Programming Language :: Python :: 3
Classifier: License :: OSI Approved :: MIT License
Classifier: Operating System :: OS Independent
Requires-Python: >=3.6
